package_schemes/__init__.py
package_schemes/patterns.py
package_schemes/interfaces/__init__.py
package_schemes/interfaces/base.py
package_schemes/interfaces/packages.py
package_schemes/interfaces/poetry_lock.py
package_schemes/interfaces/poetry_pyproject.py
package_schemes/interfaces/projects.py
package_schemes/interfaces/pyproject.py
package_schemes/interfaces/uv_lock.py
package_schemes/schemes/__init__.py
package_schemes/schemes/base.py
package_schemes/schemes/pyproject.py
package_schemes/schemes/uv_lock.py
package_schemes-0.1.2.dist-info/METADATA
package_schemes-0.1.2.dist-info/WHEEL
package_schemes-0.1.2.dist-info/top_level.txt
package_schemes-0.1.2.dist-info/RECORD
