Metadata-Version: 2.1
Name: package-schemes
Version: 0.1.2
Summary: Schemas and interfaces describing python packages
Requires-Python: >=3.9
Requires-Dist: pydantic >=2.0.0
Requires-Dist: toml >=0.10.0
Provides-Extra: test
Requires-Dist: django-storages[s3] >=1.14.4 ; extra == 'test'
